mobster/BoundedPareto.py
mobster/__init__.py
mobster/calculate_posteriors.py
mobster/example_loading.py
mobster/guide_mobster.py
mobster/interface_mobster.py
mobster/likelihood_calculation.py
mobster/model_mobster.py
mobster/model_selection_mobster.py
mobster/plotting_mobster.py
mobster/stopping_criteria.py
mobster/utils_mobster.py
mobster/__pycache__/__init__.cpython-38.pyc
mobster/__pycache__/calculate_posteriors.cpython-38.pyc
mobster/__pycache__/example_loading.cpython-38.pyc
mobster/__pycache__/guide_mobster.cpython-38.pyc
mobster/__pycache__/interface_mobster.cpython-38.pyc
mobster/__pycache__/likelihood_calculation.cpython-38.pyc
mobster/__pycache__/model_mobster.cpython-38.pyc
mobster/__pycache__/model_selection_mobster.cpython-38.pyc
mobster/__pycache__/plotting_mobster.cpython-38.pyc
mobster/__pycache__/stopping_criteria.cpython-38.pyc
mobster/__pycache__/utils_mobster.cpython-38.pyc
HMOBSTER-0.0.41.dist-info/LICENSE
HMOBSTER-0.0.41.dist-info/METADATA
HMOBSTER-0.0.41.dist-info/WHEEL
HMOBSTER-0.0.41.dist-info/top_level.txt
HMOBSTER-0.0.41.dist-info/RECORD
