Metadata-Version: 2.1
Name: HMOBSTER
Version: 0.0.41
Summary: VAF clustering for multiple karyotypes
Home-page: https://github.com/Militeee/hmobster
Author: Salvatore Milite
Author-email: militesalvatore@gmail.com
License: GPL-3.0
Keywords: DNA sequencing clonal_evolution VAF
Platform: UNKNOWN
Classifier: Development Status :: 3 - Alpha
Classifier: License :: OSI Approved :: GNU General Public License v3 (GPLv3)
Classifier: Programming Language :: Python :: 3.7
Classifier: Topic :: Scientific/Engineering :: Bio-Informatics
Requires-Dist: matplotlib (>=3.1)
Requires-Dist: pandas (>=1.0)
Requires-Dist: pyro-ppl (>=0.4)
Requires-Dist: numpy (>=1.18)
Requires-Dist: scikit-learn
Requires-Dist: seaborn
